bigletters/__init__.py
bigletters/carte.py
bigletters/fix_image.py
bigletters/main.py
bigletters-0.4.4.dist-info/DESCRIPTION.rst
bigletters-0.4.4.dist-info/METADATA
bigletters-0.4.4.dist-info/RECORD
bigletters-0.4.4.dist-info/WHEEL
bigletters-0.4.4.dist-info/entry_points.txt
bigletters-0.4.4.dist-info/metadata.json
bigletters-0.4.4.dist-info/top_level.txt
