Metadata-Version: 2.0
Name: bigletters
Version: 0.4.4
Summary: It makes letters bigger!
Home-page: https://gliggy.github.io/Gligslife/
Author: Leo Fitzpatrick
Author-email: leocfitz@gmail.com
License: UNKNOWN
Platform: UNKNOWN
Requires-Dist: easygui
